tutubo/__init__.py
tutubo/models.py
tutubo/search.py
tutubo/version.py
tutubo/ytmus.py
tutubo/pytube/__init__.py
tutubo/pytube/__main__.py
tutubo/pytube/captions.py
tutubo/pytube/cipher.py
tutubo/pytube/cli.py
tutubo/pytube/exceptions.py
tutubo/pytube/extract.py
tutubo/pytube/helpers.py
tutubo/pytube/innertube.py
tutubo/pytube/itags.py
tutubo/pytube/metadata.py
tutubo/pytube/monostate.py
tutubo/pytube/parser.py
tutubo/pytube/query.py
tutubo/pytube/request.py
tutubo/pytube/streams.py
tutubo/pytube/version.py
tutubo/pytube/contrib/__init__.py
tutubo/pytube/contrib/channel.py
tutubo/pytube/contrib/playlist.py
tutubo/pytube/contrib/search.py
tutubo-2.0.2.dist-info/METADATA
tutubo-2.0.2.dist-info/WHEEL
tutubo-2.0.2.dist-info/top_level.txt
tutubo-2.0.2.dist-info/RECORD
